{
  "updated_at": "2026-04-12T19:07:01.235201+02:00",
  "usd_eur_rate": 0.8535,
  "periods": {
    "yesterday": {
      "spent": 550,
      "cash": 896,
      "roas": 1.63,
      "calls": 4,
      "closes": 0,
      "aov": 0,
      "cost_per_call": 138,
      "cost_per_acq": 0
    },
    "today": {
      "spent": 601,
      "cash": 9,
      "roas": 0.01,
      "calls": 3,
      "closes": 0,
      "aov": 0,
      "cost_per_call": 200,
      "cost_per_acq": 0
    },
    "7d": {
      "spent": 3756,
      "cash": 14179,
      "roas": 3.78,
      "calls": 43,
      "closes": 5,
      "aov": 1640,
      "cost_per_call": 87,
      "cost_per_acq": 751
    },
    "14d": {
      "spent": 7311,
      "cash": 31628,
      "roas": 4.33,
      "calls": 97,
      "closes": 9,
      "aov": 1733,
      "cost_per_call": 75,
      "cost_per_acq": 812
    },
    "30d": {
      "spent": 17373,
      "cash": 70609,
      "roas": 4.06,
      "calls": 271,
      "closes": 21,
      "aov": 1279,
      "cost_per_call": 64,
      "cost_per_acq": 827
    }
  }
}