{
  "updated_at": "2026-04-22T12:07:01.587740+02:00",
  "usd_eur_rate": 0.8511,
  "periods": {
    "yesterday": {
      "spent": 595,
      "cash": 58,
      "roas": 0.1,
      "calls": 3,
      "closes": 0,
      "aov": 0,
      "cost_per_call": 198,
      "cost_per_acq": 0
    },
    "today": {
      "spent": 460,
      "cash": 1148,
      "roas": 2.5,
      "calls": 5,
      "closes": 0,
      "aov": 0,
      "cost_per_call": 92,
      "cost_per_acq": 0
    },
    "7d": {
      "spent": 4111,
      "cash": 11458,
      "roas": 2.79,
      "calls": 35,
      "closes": 1,
      "aov": 4000,
      "cost_per_call": 117,
      "cost_per_acq": 4111
    },
    "14d": {
      "spent": 8070,
      "cash": 21862,
      "roas": 2.71,
      "calls": 70,
      "closes": 6,
      "aov": 1533,
      "cost_per_call": 115,
      "cost_per_acq": 1345
    },
    "30d": {
      "spent": 16276,
      "cash": 67533,
      "roas": 4.15,
      "calls": 226,
      "closes": 20,
      "aov": 1475,
      "cost_per_call": 72,
      "cost_per_acq": 814
    }
  }
}