{
  "updated_at": "2026-04-17T17:07:01.374197+02:00",
  "usd_eur_rate": 0.849,
  "periods": {
    "yesterday": {
      "spent": 600,
      "cash": 4196,
      "roas": 6.99,
      "calls": 3,
      "closes": 1,
      "aov": 4000,
      "cost_per_call": 200,
      "cost_per_acq": 600
    },
    "today": {
      "spent": 510,
      "cash": 2986,
      "roas": 5.86,
      "calls": 5,
      "closes": 0,
      "aov": 0,
      "cost_per_call": 102,
      "cost_per_acq": 0
    },
    "7d": {
      "spent": 4096,
      "cash": 13342,
      "roas": 3.26,
      "calls": 36,
      "closes": 3,
      "aov": 1867,
      "cost_per_call": 114,
      "cost_per_acq": 1365
    },
    "14d": {
      "spent": 7839,
      "cash": 30224,
      "roas": 3.86,
      "calls": 81,
      "closes": 8,
      "aov": 1725,
      "cost_per_call": 97,
      "cost_per_acq": 980
    },
    "30d": {
      "spent": 16235,
      "cash": 75658,
      "roas": 4.66,
      "calls": 231,
      "closes": 22,
      "aov": 1395,
      "cost_per_call": 70,
      "cost_per_acq": 738
    }
  }
}